macchiato/__init__.py
macchiato/base.py
macchiato/config.py
macchiato/config.yml
macchiato/plot.py
macchiato/utils.py
macchiato/experiments/__init__.py
macchiato/experiments/mossbauer.py
macchiato/experiments/nmr.py
macchiato/experiments/xray.py
macchiato-0.1.1.dist-info/LICENSE
macchiato-0.1.1.dist-info/METADATA
macchiato-0.1.1.dist-info/WHEEL
macchiato-0.1.1.dist-info/top_level.txt
macchiato-0.1.1.dist-info/RECORD
