Metadata-Version: 2.1
Name: macchiato
Version: 0.1.1
Summary: Data-driven nearest neighbor models for predicting experimental results on silicon lithium-ion battery anodes.
Author-email: Francisco Fernandez <ffernandev@gmail.com>
License: MIT License
Project-URL: Homepage, https://github.com/fernandezfran/macchiato
Keywords: data-driven-model,nearest-neighbors,clustering
Classifier: Development Status :: 4 - Beta
Classifier: Intended Audience :: Science/Research
Classifier: Operating System :: OS Independent
Classifier: Programming Language :: Python
Classifier: Programming Language :: Python :: 3.8
Classifier: Programming Language :: Python :: 3.9
Classifier: Programming Language :: Python :: 3.10
Classifier: Topic :: Scientific/Engineering
License-File: LICENSE
Requires-Dist: matplotlib
Requires-Dist: mdanalysis
Requires-Dist: numpy
Requires-Dist: pandas
Requires-Dist: pyyaml
Requires-Dist: scikit-learn
Requires-Dist: scipy
Requires-Dist: importlib-metadata
